{
  "tool_id": "mcp-tool-definition-linter",
  "version": "1.1.0",
  "title": "MCP Tool-Definition Linter & Annotation Designer",
  "description": "Lints a Model Context Protocol tool definition (name, description, inputSchema, outputSchema, annotations) against JSON Schema 2020-12 and current MCP tool-naming and annotation rules, scores conformance, and designs a consistent annotation set. Reference rules are static and may age — verify against the live MCP specification.",
  "category": "cat-1",
  "tags": [
    "MCP",
    "tool definition",
    "JSON Schema 2020-12",
    "annotations",
    "linter",
    "agent tooling"
  ],
  "audience": [
    "engineer",
    "product"
  ],
  "input_schema": {
    "type": "object",
    "properties": {
      "tool_definition": {
        "type": "object",
        "description": "An MCP tool definition object with name, description, inputSchema, and optionally outputSchema and annotations."
      }
    },
    "required": [
      "tool_definition"
    ]
  },
  "output_schema": {
    "type": "object",
    "properties": {
      "score": {
        "type": "number"
      },
      "findings": {
        "type": "array",
        "items": {
          "type": "object"
        }
      },
      "annotations": {
        "type": "object"
      }
    }
  },
  "mcp_tool_definition": {
    "name": "lint_mcp_tool_definition",
    "description": "Validate an MCP tool definition against JSON Schema 2020-12 and current naming, output-schema, and annotation rules; returns findings, a conformance score, and a recommended annotation set. Use when a developer wants to check an MCP tool definition before publishing.",
    "inputSchema": {
      "type": "object",
      "properties": {
        "tool_definition": {
          "type": "object",
          "description": "The MCP tool definition to lint."
        }
      },
      "required": [
        "tool_definition"
      ]
    }
  },
  "execution": {
    "type": "browser-javascript",
    "entry": "tools/274-mcp-tool-definition-linter.html",
    "function_name": "runLinter",
    "timeout_ms": 3000
  },
  "ap2_export": true,
  "prefill": true,
  "bridge_version": "1.0"
}
